smart_pytorch/__init__.py
smart_pytorch/loss.py
smart_pytorch/smart_pytorch.py
smart_pytorch-0.0.4.dist-info/LICENSE
smart_pytorch-0.0.4.dist-info/METADATA
smart_pytorch-0.0.4.dist-info/WHEEL
smart_pytorch-0.0.4.dist-info/top_level.txt
smart_pytorch-0.0.4.dist-info/RECORD
