Metadata-Version: 2.1
Name: smart-pytorch
Version: 0.0.4
Summary: SMART Fine-Tuning - Pytorch
Home-page: https://github.com/archinetai/smart-pytorch
Author: Flavio Schneider
Author-email: archinetai@protonmail.com
License: MIT
Keywords: artificial intelligence,deep learning,fine-tuning,pre-trained
Classifier: Development Status :: 4 - Beta
Classifier: Intended Audience :: Developers
Classifier: Topic :: Scientific/Engineering :: Artificial Intelligence
Classifier: License :: OSI Approved :: MIT License
Classifier: Programming Language :: Python :: 3.6
License-File: LICENSE
Requires-Dist: torch (>=1.6)
Requires-Dist: data-science-types (>=0.2)
